setup.py
ajitesh_distributions/Binomialdistribution.py
ajitesh_distributions/Gaussiandistribution.py
ajitesh_distributions/Generaldistribution.py
ajitesh_distributions/__init__.py
ajitesh_distributions.egg-info/PKG-INFO
ajitesh_distributions.egg-info/SOURCES.txt
ajitesh_distributions.egg-info/dependency_links.txt
ajitesh_distributions.egg-info/not-zip-safe
ajitesh_distributions.egg-info/top_level.txt