Metadata-Version: 1.0
Name: ajitesh-distributions
Version: 0.1
Summary: Gaussian distributions
Home-page: UNKNOWN
Author: Ajitesh Sakaray
Author-email: sakarayajitesh@gmail.com
License: UNKNOWN
Platform: UNKNOWN
